ichrome/__init__.py
ichrome/__main__.py
ichrome/async_utils.py
ichrome/base.py
ichrome/daemon.py
ichrome/debugger.py
ichrome/exceptions.py
ichrome/logs.py
ichrome/pool.py
ichrome/py.typed
ichrome/utils.py
ichrome/http/__init__.py
ichrome/http/__main__.py
ichrome/http/app.py
ichrome/http/controller.py
ichrome/http/doc.py
ichrome/http/doc_meta.py
ichrome/schemas/daemon_config.py
ichrome/schemas/engine_schema.py
ichrome/schemas/http_schema.py
ichrome-6.0.0.dist-info/entry_points.txt
ichrome-6.0.0.dist-info/licenses/LICENSE
ichrome-6.0.0.dist-info/WHEEL
ichrome-6.0.0.dist-info/METADATA
ichrome-6.0.0.dist-info/RECORD
