Metadata-Version: 2.4
Name: ichrome
Version: 6.0.0
Summary: Chrome controller for Humans, base on Chrome Devtools Protocol(CDP) and python3.8+. Read more: https://github.com/ClericPy/ichrome.
Keywords: chrome,Chrome Devtools Protocol,daemon,CDP,browser
Author-email: ClericPy <clericpy@gmail.com>
Requires-Python: >=3.8
Classifier: License :: OSI Approved :: MIT License
Classifier: Operating System :: OS Independent
Classifier: Programming Language :: Python :: 3
Classifier: Programming Language :: Python :: 3.8
Classifier: Programming Language :: Python :: 3.9
Classifier: Programming Language :: Python :: 3.10
Classifier: Programming Language :: Python :: 3.11
Classifier: Programming Language :: Python :: 3.12
Classifier: Programming Language :: Python :: 3.13
License-File: LICENSE
Requires-Dist: psutil
Requires-Dist: aiohttp
Requires-Dist: morebuiltins>=1.3.7
Project-URL: Homepage, https://github.com/ClericPy/ichrome
Project-URL: Source, https://github.com/ClericPy/ichrome
